dl_md/__init__.py
dl_md/cli.py
dl_md-0.1.0.dist-info/LICENSE
dl_md-0.1.0.dist-info/METADATA
dl_md-0.1.0.dist-info/WHEEL
dl_md-0.1.0.dist-info/entry_points.txt
dl_md-0.1.0.dist-info/RECORD
