Metadata-Version: 2.3
Name: dl-md
Version: 0.1.0
Summary: 
Author: Don Bowman
Requires-Python: >=3.12
Classifier: Programming Language :: Python :: 3
Classifier: Programming Language :: Python :: 3.12
Classifier: Programming Language :: Python :: 3.13
Requires-Dist: click (>=8.0.0,<9.0.0)
Requires-Dist: requests (>=2.25.0,<3.0.0)
Requires-Dist: trafilatura (>=2.0.0,<3.0.0)
